README.txt
setup.py
apilimiter/__init__.py
apilimiter/admin.py
apilimiter/apps.py
apilimiter/decorators.py
apilimiter/mixin.py
apilimiter/models.py
apilimiter.egg-info/PKG-INFO
apilimiter.egg-info/SOURCES.txt
apilimiter.egg-info/dependency_links.txt
apilimiter.egg-info/not-zip-safe
apilimiter.egg-info/top_level.txt
apilimiter/management/__init__.py
apilimiter/management/commands/__init__.py
apilimiter/management/commands/collectlimiter.py
apilimiter/migrations/0001_initial.py
apilimiter/migrations/0002_dailylimits_time_left.py
apilimiter/migrations/__init__.py