Metadata-Version: 1.1
Name: apilimiter
Version: 1.0.4
Summary: View limiter for django
Home-page: https://github.com/mymusise/django-view-limiter
Author: mymusise
Author-email: mymusise1@gmail.com
License: MIT
Keywords: apilimiter api limiter django view
Platform: UNKNOWN
Classifier: Development Status :: 5 - Production/Stable
Classifier: Environment :: Web Environment
Classifier: Intended Audience :: Developers
Classifier: License :: OSI Approved :: MIT License
Classifier: Framework :: Django
Classifier: Programming Language :: Python
Classifier: Programming Language :: Python :: 3
Classifier: Programming Language :: Python :: 2.7
Classifier: Topic :: Software Development
